maya_zen_tools/__init__.py
maya_zen_tools/__main__.py
maya_zen_tools/_create.py
maya_zen_tools/_transform.py
maya_zen_tools/_traverse.py
maya_zen_tools/_ui.py
maya_zen_tools/_utilities.py
maya_zen_tools/errors.py
maya_zen_tools/flood.py
maya_zen_tools/install.py
maya_zen_tools/loft.py
maya_zen_tools/loop.py
maya_zen_tools/menu.py
maya_zen_tools/options.py
maya_zen_tools/py.typed
maya_zen_tools/startup.py
maya_zen_tools/uninstall.py
maya_zen_tools/upgrade.py
maya_zen_tools-0.1.83.dist-info/METADATA
maya_zen_tools-0.1.83.dist-info/WHEEL
maya_zen_tools-0.1.83.dist-info/RECORD
