Metadata-Version: 2.4
Name: maya-zen-tools
Version: 0.1.83
Summary: Zen Tools for Maya
Project-URL: Repository, https://github.com/enorganic/maya-zen-tools
Author-email: david@belais.me
License-Expression: MIT
Keywords: autodesk,maya,zen-tools
Requires-Python: ~=3.8
Requires-Dist: more-itertools~=10.7
Requires-Dist: platformdirs~=4.3
